{
  "count": 123,
  "communes": 23,
  "adr": {
    "Studio": 46,
    "T3": 75,
    "T2": 52,
    "T5": 250,
    "T4": 96,
    "T6+": 350
  },
  "featured": [
    {
      "id": 470939,
      "name": "Le Verger Secret",
      "city": "Saint-Loup-de-Varennes",
      "guests": 14,
      "bedrooms": 5,
      "bathrooms": 3,
      "price": 460,
      "rating": 9.1,
      "cover": "https://hostaway-platform.s3.us-west-2.amazonaws.com/listing/136426-470939-fes1SCAPiMY--SDOySOBZ2Q1amGBY-Um--gkrv3IWwnoU-695450d6e7619",
      "photos": [
        "https://hostaway-platform.s3.us-west-2.amazonaws.com/listing/136426-470939-fes1SCAPiMY--SDOySOBZ2Q1amGBY-Um--gkrv3IWwnoU-695450d6e7619",
        "https://hostaway-platform.s3.us-west-2.amazonaws.com/listing/136426-470939-8YnaaOgZl1fkRZBSMqvlE1i8OmvN121mZHnTUrijM0w-6956b166dd661",
        "https://hostaway-platform.s3.us-west-2.amazonaws.com/listing/136426-470939-fchFrIK1t5rgq2h1vJrzraUqn5hNn9zI9pjazUc4Cto-6955278f5ffca",
        "https://hostaway-platform.s3.us-west-2.amazonaws.com/listing/136426-470939-wedFgGA-Ttus8KxyXwAxIq6pF-YkEmlZumYLB0yhv--o-6955279fa4be4",
        "https://hostaway-platform.s3.us-west-2.amazonaws.com/listing/136426-470939-jzqnXYONlebEBaSnHFGwleuI4m7Ic6wHlHcFPJbSRPk-695450d5ba14d",
        "https://hostaway-platform.s3.us-west-2.amazonaws.com/listing/136426-470939-7GCdUzoZngLxahFLietT7fmo1e--ir7aAKrf90RF2s6s-695527947851c",
        "https://hostaway-platform.s3.us-west-2.amazonaws.com/listing/136426-470939-iQ2-tM62W5w--WrEfjSlZ--2I5-ydWU5--YKflVQhzxXhY-695450cd27c37",
        "https://hostaway-platform.s3.us-west-2.amazonaws.com/listing/136426-470939-Q4EehBI4rfQRSI8I1AQbbQw0jAvgXTzPnzLoegeIv-8-695450cb59cfa",
        "https://hostaway-platform.s3.us-west-2.amazonaws.com/listing/136426-470939-IDOq0q1g6--eGG4q8iKWWD-ld3XI--1-877zBxNM4DOTk-6955278734111",
        "https://hostaway-platform.s3.us-west-2.amazonaws.com/listing/136426-470939---e--B3X9zirvbifbiXjszisUpdjFFQFhVDLOwxFhofVE-695450c991899",
        "https://hostaway-platform.s3.us-west-2.amazonaws.com/listing/136426-470939-MZERLq0e35nxdqJTIdorbpD5EJlcU8DYn6WuaiacXBE-6955278875e74",
        "https://hostaway-platform.s3.us-west-2.amazonaws.com/listing/136426-470939-gA8j2EajHDrYv0TTjuJK60Mw3kAqTfcRcm-yrnd-GZo-695450b843c94"
      ],
      "description": "Découvrez et savourez le charme unique de notre demeure de 280m2, situé à Saint-Loup-de-Varennes. Ancien corps de ferme complètement rénové, l'endroit est idéal pour accueillir confortablement une grande famille, des travailleurs ou encore plusieurs amis souhaitant se rassembler. À proximité de Chalon-sur-Saône ainsi que de l'autoroute A6, l'emplacement est parfait pour un séjour en toute sérénité. Venez vivre une expérience agréable et reposante hors de l'urbanisme ! ✔ REZ DE CHAUSSÉE ✔ → Hall d'entrée : Dès votre entrée dans la maison, laissez-vous séduire par un hall d'accueil spacieux et élégamment épuré. Juste à côté de la porte principale, un petit meuble à tiroirs vous accueille, pratique pour déposer vos clés et petits objets. Adjacente, une porte s'ouvre sur un espace fonctionnel équipé d'un porte-manteau et d'un meuble dédié à vos chaussures. À votre gauche, un placard intégré offre une solution de rangement supplémentaire, tandis qu'en face de vous, un MAJESTUEUX MIROIR de plus de 2 mètres de haut, d'inspiration baroque, capture votre reflet et agrandit visuellement l'espace. Cet objet d'art est accompagné d'une chaise au design capitonné suggérant une fusion de styles ancien et nouveau, tandis que les appliques murales décoratives ajoutent une note de design industriel à l'ensemble. Sur votre gauche, après le placard intégré, se dresse une console en bois au design ",
      "amenities": [
        "Wifi",
        "Cuisine équipée",
        "Parking gratuit",
        "Climatisation",
        "Lave-vaisselle",
        "Télévision",
        "Chauffage",
        "Jardin",
        "Linge & nécessaire",
        "Fer à repasser",
        "Animaux acceptés",
        "Micro-ondes",
        "Four",
        "Réfrigérateur"
      ],
      "lat": 46.7312999,
      "lng": 4.8628258,
      "mapx": 78.1,
      "mapy": 72.7,
      "type": "T6+",
      "cleaningFee": 300,
      "deposit": 400,
      "markup": 1.05,
      "minNights": 1,
      "currency": "EUR",
      "instant": 1,
      "reviewCount": 23,
      "reviews": [
        {
          "name": "Voyageur",
          "text": "Le logement est parfait pour accueillir grande famille ou bande de copains. Spacieux, organisé et propre. Une belle météo nous à permis de profiter de l'extérieur. Je recommande sans problème. Merci Anthony et à bientôt 👍"
        },
        {
          "name": "Mohammed",
          "text": "Très beau séjour. Maison très spacieuse et très agréable à vivre. La cuisine, le salon, les chambres; tout est grand, propre et neuf. Je recommande."
        },
        {
          "name": "Tommy",
          "text": "Très jolie maison, propre et fidèle à la description, je recommande"
        }
      ]
    },
    {
      "id": 465573,
      "name": "Chalon Hacienda",
      "city": "Chalon-sur-Saône",
      "guests": 8,
      "bedrooms": 4,
      "bathrooms": 2,
      "price": 400,
      "rating": 9.3,
      "cover": "https://hostaway-platform.s3.us-west-2.amazonaws.com/listing/136426-465573-TVtah0ZdUKTUfP-4YF0VvAC7mj7qf-ZGlhexHuic--XQ-693d6375bd308",
      "photos": [
        "https://hostaway-platform.s3.us-west-2.amazonaws.com/listing/136426-465573-TVtah0ZdUKTUfP-4YF0VvAC7mj7qf-ZGlhexHuic--XQ-693d6375bd308",
        "https://hostaway-platform.s3.us-west-2.amazonaws.com/listing/136426-465573-JT626tld4VWdPU9giiOQW6AR-GjNXPfi2-Zt7ZBr2Fg-693d637431eca",
        "https://hostaway-platform.s3.us-west-2.amazonaws.com/listing/136426-465573-5N4GDvVilim-glAg--MuWPJ8XPqj7PKfwEXWNop5Q39g-693d636fef9ce",
        "https://hostaway-platform.s3.us-west-2.amazonaws.com/listing/136426-465573-VrkDHueQGd2X1jDpOs4BzluFKh1Kpt3aSuG--3fjCNME-693d63862d72e",
        "https://hostaway-platform.s3.us-west-2.amazonaws.com/listing/136426-465573-SeeTbQVk3aHSnFwPqyp6vcZCcAfkG3QKkbDE05GycIc-693d6a6bef681",
        "https://hostaway-platform.s3.us-west-2.amazonaws.com/listing/136426-465573-4SLO64HkgIkdVLyfMKLQixAlRAHT5L51D1AwqPT7gAA-693d6388b6979",
        "https://hostaway-platform.s3.us-west-2.amazonaws.com/listing/136426-465573-0u9UjpXDuyK-qgBe0RdPptWvCvscEHRzpHbnw1JMU9o-693d639340803",
        "https://hostaway-platform.s3.us-west-2.amazonaws.com/listing/136426-465573-N8Xx03KU0z97KenIHzS839jmnH--LOiochdz5UVIc8d8-693d6a6e0c8a6",
        "https://hostaway-platform.s3.us-west-2.amazonaws.com/listing/136426-465573-Yb9Wl--0TgxYH3JfextM9h7zDvJBL4AigsDLs74CyhuI-693d63657ad9b",
        "https://hostaway-platform.s3.us-west-2.amazonaws.com/listing/136426-465573-kBRthxL2Zgd0aixpGS0U1wmKtYCVHzuTvLGIvpvZlV8-693d6a6ce61e5",
        "https://hostaway-platform.s3.us-west-2.amazonaws.com/listing/136426-465573-4oXkqsGpHohUljKd-9T3OpRHY7--WlI7r9Q1woejObNE-693d6a6f17487",
        "https://hostaway-platform.s3.us-west-2.amazonaws.com/listing/136426-465573-9W3PKGpsBF4D0XrolqBscov76wOcC4oK--S91RwvpTqI-693d6397cac63"
      ],
      "description": "Découvrez notre somptueuse maison de 127m2, situé Avenue Boucicaut. Idéal pour accueillir confortablement une famille, des amis ou encore des voyageurs d'affaires. Situé proche du centre ville et à proximité immédiate du périphérique, l'emplacement est idéal pour éviter le stress des bouchons. Venez découvrir un lieu rempli de charme à Chalon-sur-Saône ! Dès votre entrée, laissez-vous séduire par une pièce de vie spacieuse et lumineuse, divisée en deux espaces distincts. LE SALON, à l’ambiance cosy, est aménagé avec deux fauteuils confortables, une table basse, un canapé moelleux, et une TV SUSPENDUE. Quelques plantes décoratives et un grand miroir verrière à structure dorée reflète la lumière naturelle, apportant un cachet indéniable à cet espace raffiné. De l’autre côté, UNE CUISINE en U entièrement équipée vous invite à préparer vos plats préférés (équipée d’une machine à café Nespresso et d’une enceinte Bluetooth). Entre ces deux univers, UN ESPACE REPAS accueillant jusqu’à 8 convives vous attend, sublimé par un grand miroir qui agrandit visuellement l’espace. Attenant à la cuisine, une première SALLE D’EAU élégante propose une douche aux finitions dorées, un meuble vasque avec miroir et un WC, parfaitement intégrés à l’esthétique du logement. Direction l’étage, où TROIS CHAMBRES raffinées vous attendent ainsi qu’un WC indépendant. La première et la troisième chambres sont ",
      "amenities": [
        "Wifi",
        "Cuisine équipée",
        "Parking gratuit",
        "Climatisation",
        "Lave-vaisselle",
        "Télévision",
        "Chauffage",
        "Jardin",
        "Balcon",
        "Linge & nécessaire",
        "Fer à repasser",
        "Animaux acceptés",
        "Micro-ondes",
        "Four"
      ],
      "lat": 46.7875024,
      "lng": 4.8395616,
      "mapx": 77.59,
      "mapy": 70.37,
      "type": "T5",
      "cleaningFee": 95,
      "deposit": 400,
      "markup": 1.05,
      "minNights": 1,
      "currency": "EUR",
      "instant": 1,
      "reviewCount": 9,
      "reviews": [
        {
          "name": "Voyageur",
          "text": "Nous avons passé un agréable séjour dans le logement d'Anthony. Le logement correspondait à nos critères et nous l'avons trouvé propre et bien décoré. je recommande"
        },
        {
          "name": "Jonathan",
          "text": "Le logement correspond totalement à l’annonce, c’est très propre et de bon goût, je recommande !"
        }
      ]
    },
    {
      "id": 468351,
      "name": "Belle maison rénovée avec jacuzzi",
      "city": "Saint-Rémy",
      "guests": 10,
      "bedrooms": 4,
      "bathrooms": 2,
      "price": 260,
      "rating": 8.8,
      "cover": "https://hostaway-platform.s3.us-west-2.amazonaws.com/listing/136426-468351-bDbenOl9gJ30WvspCQpvWGz-r--XKn4MwjB--hEJBW6EQ-6a2f1a6b1b1e8",
      "photos": [
        "https://hostaway-platform.s3.us-west-2.amazonaws.com/listing/136426-468351-bDbenOl9gJ30WvspCQpvWGz-r--XKn4MwjB--hEJBW6EQ-6a2f1a6b1b1e8",
        "https://hostaway-platform.s3.us-west-2.amazonaws.com/listing/136426-468351-C1IUWTXuZGuYM3DGE--olutbJ53lpaZhUG-89uEsKAz0-6a2f1a23941c3",
        "https://hostaway-platform.s3.us-west-2.amazonaws.com/listing/136426-468351-ijZd2F--vDfNq29v1YLq9Xu7JiQ1p8U06d-IzejvGRj8-6a2f1a2854964",
        "https://hostaway-platform.s3.us-west-2.amazonaws.com/listing/136426-468351-TKbjGyGq1iN47xpTdyEn2KvTUw6e2cgb1nhMQA3BZg8-6a2f1a3230901",
        "https://hostaway-platform.s3.us-west-2.amazonaws.com/listing/136426-468351-lzReULyjSVUkscWAepGl2o5yQW9--h5pZV-C5iqfhGGY-6a2f1a03c40a9",
        "https://hostaway-platform.s3.us-west-2.amazonaws.com/listing/136426-468351-8HkLHNbks94fG-JiHcm1bZT--V--vgE5LUbFjl4RtI-ho-6a2f1a4408b4e",
        "https://hostaway-platform.s3.us-west-2.amazonaws.com/listing/136426-468351-qUJ--TQ1ayV1XBCWZhuTMKJFTbwg46rUac5vmLri0xt4-6a2f1a07b7583",
        "https://hostaway-platform.s3.us-west-2.amazonaws.com/listing/136426-468351-hlzSaqEjOio7--SJcXCvilaPx8BsWF--jskrYz--8dKD8-6a2f1a11f08d2",
        "https://hostaway-platform.s3.us-west-2.amazonaws.com/listing/136426-468351-H4IVChyAXBSoTrhSnIRdr-M598oER1wAXdBVHLRBODg-6a2f19f407891",
        "https://hostaway-platform.s3.us-west-2.amazonaws.com/listing/136426-468351-nPY--PahU-w1CO21eqAhUBsJvDsFyUskZmhaPo7TenNU-6a2f1a39885c5",
        "https://hostaway-platform.s3.us-west-2.amazonaws.com/listing/136426-468351-BV-FyvSpG27EIslwwQu6bVbnrr4ZSGf165dvccYcULc-6a2f1a3ebbae4",
        "https://hostaway-platform.s3.us-west-2.amazonaws.com/listing/136426-468351-DKxuK2xhWanjOQAFp--Mw0UU622hSP--WJA--51x0nYj3c-6a2f19ef2e271"
      ],
      "description": "La maison est idéalement située au coeur de Saint-Rémy, à proximité des commerces. Un jaccuzi, qui vous permettra de profiter d'agréables moments de détente, se trouve dans le jardin, à l'arrière de la maison. logement affiche un style résolument unique. En entrant au rez-de-chaussée de la maison, vous aurez accès à une petite salle de bains avec douche, à des toilettes, à deux chambres: Une avec lit double et l'autre avec un lit double et un canapé (Clic-clac), à une salle de bain avec baignoire et douche, ainsi qu'à une buanderie. L'escalier qui se trouve dans le hall d'entrée vous mènera au premier étage où se trouvent une vaste pièce équipée d'une grande table et d'un coin salon avec un canapé deux places et une télévision. A cet étage se trouvent également deux chambres, une équipée d'un lit double, la seconde équipée de deux lits simples. La dernière pièce de ce niveau est une cuisine équipée spacieuse. Les voyageurs ont accès à toutes les pièces de la maison. Nous sommes disponible via l'application Airbnb de 8h à 21h. Au sud de la Bourgogne, Chalon-sur-Saône bénéficie d’une situation géographique privilégiée. Située dans le département de Saône-et-Loire, Chalon est à 120 km au nord de Lyon et à 70 km au sud de Dijon. L’arrivée de la ligne LGV Rhin-Rhône en 2012 a placé Strasbourg à 3h, Paris à 2h30 et Lyon à 1h. La Saône divise la ville en deux bras qui enserrent l’île ",
      "amenities": [
        "Wifi",
        "Cuisine équipée",
        "Parking gratuit",
        "Jacuzzi",
        "Climatisation",
        "Sèche-linge",
        "Lave-vaisselle",
        "Télévision",
        "Chauffage",
        "Jardin",
        "Balcon",
        "Linge & nécessaire",
        "Fer à repasser",
        "Micro-ondes"
      ],
      "lat": 46.771921,
      "lng": 4.8322513,
      "mapx": 77.42,
      "mapy": 71.01,
      "type": "T5",
      "cleaningFee": 150,
      "deposit": 400,
      "markup": 1.05,
      "minNights": 1,
      "currency": "EUR",
      "instant": 1,
      "reviewCount": 42,
      "reviews": [
        {
          "name": "Paul",
          "text": "Très bon séjour sur place pour le marathon de Chalon-sur-Saône. L’hôte nous a accordé de partir un petit plus tard le dimanche afin de nous reposer. Une belle attention pour ponctuer un passage dans cette belle région"
        },
        {
          "name": "Justine",
          "text": "Très bon séjour passé dans cette maison ! Top d’avoir des serviettes et du linge de lit de qualité. Bien équipée et propre. Hôte très réactif et sympathique"
        },
        {
          "name": "Voyageur",
          "text": "Belle maison de ville rénovée, logement propre, prix raisonnable, facilité pour garer les voitures, petit plus avec le jacuzzi propre et chaud. Parfait !"
        }
      ]
    },
    {
      "id": 475670,
      "name": "La Cave des Miracles",
      "city": "Dracy-le-Fort",
      "guests": 8,
      "bedrooms": 4,
      "bathrooms": 3,
      "price": 250,
      "rating": 9.5,
      "cover": "https://hostaway-platform.s3.us-west-2.amazonaws.com/listing/136426-475670-zGKcE0tzCU2mv0zqYCpfVhLvbig8Fjpgya189Pcz0ds-6967426b5bd2f",
      "photos": [
        "https://hostaway-platform.s3.us-west-2.amazonaws.com/listing/136426-475670-zGKcE0tzCU2mv0zqYCpfVhLvbig8Fjpgya189Pcz0ds-6967426b5bd2f",
        "https://hostaway-platform.s3.us-west-2.amazonaws.com/listing/136426-475670-Slrx5tdo-t24-lYg52OTHkhzKX--xw3QIrpjukS2Pg--4-696742651ac73",
        "https://hostaway-platform.s3.us-west-2.amazonaws.com/listing/136426-475670-gkoCiCpKNkMWo7HBkgB2seJQ1HpA6qPHODXAapXffyg-69674251c26e3",
        "https://hostaway-platform.s3.us-west-2.amazonaws.com/listing/136426-475670-U0cdJJs--ZJ5YKdVYP3q-37Cqn8r2lLgkUi6ltmvXaNI-6966a114c711e",
        "https://hostaway-platform.s3.us-west-2.amazonaws.com/listing/136426-475670-wwDv12jurq-EZuGjPoz6dRmfufSS8KOhyJbet2ZK--i0-696605284d062",
        "https://hostaway-platform.s3.us-west-2.amazonaws.com/listing/136426-475670-sbQqdfVyniQcCuYNoIPVtVCQCpEfTHfhYI1nmoUu5v4-6967bc521796d",
        "https://hostaway-platform.s3.us-west-2.amazonaws.com/listing/136426-475670-KeP3e8dQTcdqcv1MH7bM--xG9eJxUqy8Ho6jEPPjHdT8-696742642eb77",
        "https://hostaway-platform.s3.us-west-2.amazonaws.com/listing/136426-475670-xrH-TW5AlVW9M3BJIOkGyBjedc05qTicljurb-pRDDc-696820680cde9",
        "https://hostaway-platform.s3.us-west-2.amazonaws.com/listing/136426-475670-8Juh37Fxyp5PFQEF3q5FKO0zKV7oZjIe3f42xI01qss-6967bc4e07e1d",
        "https://hostaway-platform.s3.us-west-2.amazonaws.com/listing/136426-475670-mF1U52SpV1cT9fU5oal7V9LTH9hQ63s-I5Cnzn4TXmo-6967fe30dad5e",
        "https://hostaway-platform.s3.us-west-2.amazonaws.com/listing/136426-475670-bILBSmspHPQvyQqGWqovh0rKLxWK7R5AQF--3gvuTZWk-6967bc4eed9c4",
        "https://hostaway-platform.s3.us-west-2.amazonaws.com/listing/136426-475670-EanJr7REYfLEhXJJN9Nfo8blhsijVaN2jMW53Ojmpcc-6967426a6a43f"
      ],
      "description": "Découvrez et savourez le charme unique de Dracy-le-Fort de part notre maison de 150m2. Parfait pour accueillir confortablement une famille, des amis ou encore des voyageurs d'affaires. L’emplacement est idéal si vous êtes en quête d’inspiration, d'aventure ou de détente. Proche des plus grands domaines viticoles de France, venez vivre un magnifique séjour ! Franchissez le seuil de la maison et laissez-vous envelopper par une atmosphère à la fois authentique et contemporaine, où chaque détail semble avoir été pensé pour le confort et la sérénité. Le mariage subtil entre les murs en pierre, le parquet chaleureux et les teintes naturelles instaure dès l’entrée une ambiance douce et apaisante, propice à la détente. L’espace de vie s’articule autour d’une cuisine entièrement équipée, ouverte et conviviale. Ses lignes sobres et modernes contrastent élégamment avec la pierre apparente, créant un équilibre parfait entre tradition et modernité. Vous y trouverez tout le nécessaire pour préparer vos repas dans un cadre inspirant, baigné d’une lumière naturelle qui traverse généreusement la pièce. Dans le prolongement, un salon raffiné vous invite à la détente. Ses assises confortables, ses touches de décoration soigneusement sélectionnées et la chaleur du bois en font un lieu idéal pour partager un moment en famille ou entre amis. Les jeux de lumière, associés à la texture brute des murs,",
      "amenities": [
        "Wifi",
        "Cuisine équipée",
        "Parking gratuit",
        "Climatisation",
        "Lave-vaisselle",
        "Télévision",
        "Chauffage",
        "Jardin",
        "Linge & nécessaire",
        "Fer à repasser",
        "Animaux acceptés",
        "Micro-ondes",
        "Four",
        "Réfrigérateur"
      ],
      "lat": 46.7964801,
      "lng": 4.7644667,
      "mapx": 75.92,
      "mapy": 69.99,
      "type": "T5",
      "cleaningFee": 140,
      "deposit": 400,
      "markup": 1.05,
      "minNights": 2,
      "currency": "EUR",
      "instant": 1,
      "reviewCount": 41,
      "reviews": [
        {
          "name": "Aurelien",
          "text": "Logement correspondant parfaitement à la description. Décoré avec goût, cave magnifique, pièce de vie très agréable à vivre. Juste dommage qu il n y est pas 8 verres à vin afin de profiter pleinement de cette fabuleuse cave."
        },
        {
          "name": "Voyageur",
          "text": "Maison idéale pour plusieurs couples d’amis ou une famille, tout était pratique et confortable. Petite attention locale à l’arrivée. On n’hésitera pas à y revenir si nous sommes dans le coin."
        },
        {
          "name": "Claire",
          "text": "Très belle maison dans un charmant village avec de belles balades à faire Bonne literie et espaces bien délimités nous avons passé un bon WE"
        }
      ]
    },
    {
      "id": 465755,
      "name": "Les Vagastines 2",
      "city": "Saint-Germain-du-Plain",
      "guests": 10,
      "bedrooms": 8,
      "bathrooms": 5,
      "price": 250,
      "rating": 10,
      "cover": "https://hostaway-platform.s3.us-west-2.amazonaws.com/listing/136426-465755-nMoUuVtyUn3CI-M1M0OQwd080FxnqMPBBW4amQReQy0-69eb65bee0e63",
      "photos": [
        "https://hostaway-platform.s3.us-west-2.amazonaws.com/listing/136426-465755-nMoUuVtyUn3CI-M1M0OQwd080FxnqMPBBW4amQReQy0-69eb65bee0e63",
        "https://hostaway-platform.s3.us-west-2.amazonaws.com/listing/136426-465755-0jycRI6y3HyH9O9--BeV8S--ZGmEsJT1JmaD-aJCxBntw-69eb64e5674af",
        "https://hostaway-platform.s3.us-west-2.amazonaws.com/listing/136426-465755-BNRU9JlLijF0nBCHRzDF-q6lVIeVtTPwfFcEdoRCWwE-69eb64ff737ba",
        "https://hostaway-platform.s3.us-west-2.amazonaws.com/listing/136426-465755-uR-MbYmjlXM7UBTCcOG----tesIibsiQWmsUj--GJrkI--0-69eb65a256a5c",
        "https://hostaway-platform.s3.us-west-2.amazonaws.com/listing/136426-465755-1lhCPY8yWCpB2xirwF-aZeor0ToDWnyu4q80yclMU18-69eb651bdc788",
        "https://hostaway-platform.s3.us-west-2.amazonaws.com/listing/136426-465755-StV-Es5eDmHMzgQ9U2wh3iuPO6GHYKVk--aWIkVQIjVo-69eb65b06e39c",
        "https://hostaway-platform.s3.us-west-2.amazonaws.com/listing/136426-465755-BhgZ-udZEAxMyL6e3DhrgKp5akYVjU81b6ghGP3kpX4-69eb652683fc7",
        "https://hostaway-platform.s3.us-west-2.amazonaws.com/listing/136426-465755---UySNxLPQ--QGVAsJZKdXGb2----Yj5FcwcyuCabPmTDI4-69eb64ed6961e",
        "https://hostaway-platform.s3.us-west-2.amazonaws.com/listing/136426-465755-iB2u3gsb1yQZvTzR6dPR6Kz--YmpBVsV8I-O0HJBPvDc-69eb655492d1b",
        "https://hostaway-platform.s3.us-west-2.amazonaws.com/listing/136426-465755-xbRASymRLuMudvj5plLbt9SN1gA95z4nB4Ss2gf6q4E-69eb656116117",
        "https://hostaway-platform.s3.us-west-2.amazonaws.com/listing/136426-465755-ONE4j19BXM1y-ll3dKo2ZYG0BZl41JE0obEpeihi1p0-69eb64ce7e202",
        "https://hostaway-platform.s3.us-west-2.amazonaws.com/listing/136426-465755-3pkHDAGkxDNdN4fdXbxYUy--BpH2Q76dBwuidaulNoKA-69eb65314bbf6"
      ],
      "description": "Bienvenue dans nos deux gîtes en plein coeur de bresse ! Deux maisons indépendantes au cœur de la campagne : un double séjour pour des moments inoubliables Situées sur la même propriété et séparées par une charmante cour, ces deux maisons indépendantes vous offrent la possibilité de séjourner ensemble tout en bénéficiant de votre intimité. Que vous soyez une grande famille, deux familles amies ou un groupe souhaitant combiner convivialité et indépendance, ce lieu est idéal. Maison 1 – Charme, confort et piscine intérieure Dès l’entrée, vous serez séduit par une pièce de vie chaleureuse et baignée de lumière naturelle, composée d’un salon cosy ouvert sur une cuisine entièrement équipée. Une table à manger pour 6 personnes trône au centre, idéale pour partager des repas conviviaux. Le salon, délimité par un grand tapis, est équipé d’un canapé confortable, d’une télévision, d’une table basse et d’une porte-fenêtre donnant directement sur le jardin privatif. La cuisine en longueur, moderne et fonctionnelle, vous permet de cuisiner en toute autonomie. Attenante à celle-ci, se trouve une véritable perle : une piscine intérieure, parfaite pour des instants de détente en toute saison. Cette maison comprend également : Un WC indépendant Une buanderie complète (lave-linge, sèche-linge, douche, meuble vasque) Un coin détente avec vue imprenable sur la campagne environnante, grâce aux gran",
      "amenities": [
        "Wifi",
        "Cuisine équipée",
        "Parking gratuit",
        "Piscine",
        "Climatisation",
        "Lave-vaisselle",
        "Télévision",
        "Chauffage",
        "Linge & nécessaire",
        "Fer à repasser",
        "Micro-ondes",
        "Four",
        "Réfrigérateur",
        "Séjours longue durée"
      ],
      "lat": 46.6864496,
      "lng": 4.9791171,
      "mapx": 80.68,
      "mapy": 74.57,
      "type": "T6+",
      "cleaningFee": 220,
      "deposit": 400,
      "markup": 1.15,
      "minNights": 1,
      "currency": "EUR",
      "instant": 1,
      "reviewCount": 3,
      "reviews": [
        {
          "name": "Martin",
          "text": "Un séjour particulièrement reposant pour passer Noël en famille. La maison était parfaite À La fois pour adultes et enfants avec une piscine très sécurisée ! Nous reviendrons avec grand plaisir !"
        },
        {
          "name": "Voyageur",
          "text": "deux très beaux gîtes où on se sent bien 👍 très bonne communication en amont pour la préparation du séjour. Merci"
        }
      ]
    },
    {
      "id": 468463,
      "name": "Les Vignes Rouges",
      "city": "Givry",
      "guests": 8,
      "bedrooms": 3,
      "bathrooms": 2,
      "price": 250,
      "rating": 9.5,
      "cover": "https://hostaway-platform.s3.us-west-2.amazonaws.com/listing/136426-468463-zuoEeX--fFdIDlkJn7fYgS7vAb9DNq57--41eHpgxVrKA-694a805d2594a",
      "photos": [
        "https://hostaway-platform.s3.us-west-2.amazonaws.com/listing/136426-468463-zuoEeX--fFdIDlkJn7fYgS7vAb9DNq57--41eHpgxVrKA-694a805d2594a",
        "https://hostaway-platform.s3.us-west-2.amazonaws.com/listing/136426-468463-fXnI69iLfxaR6EF2paM67MpVkoa-jxZy8h5jFGAHkpY-694a803834bb7",
        "https://hostaway-platform.s3.us-west-2.amazonaws.com/listing/136426-468463-MJcxlS8vMa5n7J0CCLUGtt4Oo4795EGBtxaeo3nrXSk-694fe63a811e1",
        "https://hostaway-platform.s3.us-west-2.amazonaws.com/listing/136426-468463-mKkCKMp3L8nk-zOv8V8wumLH6qsURyGDgu4ePCjnV--A-694d4f7b9431c",
        "https://hostaway-platform.s3.us-west-2.amazonaws.com/listing/136426-468463-IzAwgLqVRf9HyqByb4PLfn8-6XRcRqhDnsylpLKqWm4-694d4f7a4c166",
        "https://hostaway-platform.s3.us-west-2.amazonaws.com/listing/136426-468463-Srn7SaWe6NYPnecvcEsNXea4ML0buYuEdgo5ny6VfGU-69484b4e9bf19",
        "https://hostaway-platform.s3.us-west-2.amazonaws.com/listing/136426-468463-mQ1tlW3HfV5T--MKBnofRAA7IZEg--SyX8I0ewSi9b4xA-694fe63b80678",
        "https://hostaway-platform.s3.us-west-2.amazonaws.com/listing/136426-468463-nhOF2BAny12RUhRNsaQW--ji0398CvyIIyOgThscpmOA-694c572b466fa",
        "https://hostaway-platform.s3.us-west-2.amazonaws.com/listing/136426-468463-kNtgcs-07jlZznnhpaNNm9-7lubtvNxZT--7Hnj37Xh4-69484b491d7ca",
        "https://hostaway-platform.s3.us-west-2.amazonaws.com/listing/136426-468463-PEsIqWCldF7PJid3oCWPlAFUivRBotm--xgqqcHWX6fY-694a803d7ded8",
        "https://hostaway-platform.s3.us-west-2.amazonaws.com/listing/136426-468463-ccJPdjD4i3o--ek6AJGPwnWT4b-XBE5g1wqNOWRuxU3E-694b69687b4a2",
        "https://hostaway-platform.s3.us-west-2.amazonaws.com/listing/136426-468463-GvKPxWZRYTBPvtAxgeh8QDzrVweDdbDjXyX4hwTT8CQ-6951b864cbf23"
      ],
      "description": "Au cœur de la Bourgogne, entre nature préservée, roche et vignes, découvrez cette magnifique maison de caractère nichée dans les hauteurs de Givry. Ce village emblématique de la Côte Chalonnaise, réputé pour ses vins et son art de vivre, offre un décor pittoresque à cette demeure unique. Véritable havre de paix, elle séduira aussi bien les familles que les voyageurs en quête d’authenticité, de calme et de sérénité. Dès le portail franchi, vous serez saisis par l’atmosphère paisible et dépaysante des lieux. Un lieu coupé du monde, baigné de lumière, où l’on respire la tranquillité. Dès l’entrée, un vaste séjour vous accueille avec, en son centre, une grande table à manger pouvant réunir jusqu’à 8 convives. Le charme opère immédiatement : poutres apparentes, murs aux teintes inspirées de la vigne, et matières naturelles offrent une ambiance élégante et authentique. À votre gauche, une cuisine ouverte entièrement équipée vous invite à cuisiner dans un espace fonctionnel, doté d’un îlot central parfait pour se retrouver autour d’un verre ou d’un bon repas. Appareil à raclette, micro-ondes, frigo, vaisselle, tout y est. La cuisine ouvre également sur un espace cellier discret, parfait pour stocker vos provisions. Dans la même pièce, une cheminée décorative (non fonctionnelle) ajoute une touche de charme à l’ensemble et complète cette atmosphère chaleureuse, typique des belles maison",
      "amenities": [
        "Wifi",
        "Cuisine équipée",
        "Parking gratuit",
        "Climatisation",
        "Lave-vaisselle",
        "Télévision",
        "Chauffage",
        "Jardin",
        "Balcon",
        "Cheminée",
        "Entrée privée",
        "Linge & nécessaire",
        "Fer à repasser",
        "Micro-ondes"
      ],
      "lat": 46.776237,
      "lng": 4.717755,
      "mapx": 74.88,
      "mapy": 70.84,
      "type": "T4",
      "cleaningFee": 140,
      "deposit": 400,
      "markup": 1.05,
      "minNights": 3,
      "currency": "EUR",
      "instant": 1,
      "reviewCount": 10,
      "reviews": [
        {
          "name": "Voyageur",
          "text": "j’ai passé un super week end dans ce airbnb, conforme au photo et à la description, le logement était très propre juste un peu compliqué à trouver mais à part ça tout était nickel, je recommande vivement"
        },
        {
          "name": "Olivier",
          "text": "Excellent séjour, très au calme. Quelques ajustements au debut mais le propriétaire a été très réactif."
        },
        {
          "name": "Mohammed",
          "text": "Merci pour ce séjour très agréable. Tout a été parfait. Je recommande fortement. Merci"
        }
      ]
    },
    {
      "id": 474343,
      "name": "Charmant gîte 3* entouré de vignes à Givry",
      "city": "Givry",
      "guests": 6,
      "bedrooms": 2,
      "bathrooms": 1,
      "price": 120,
      "rating": 9.7,
      "cover": "https://hostaway-platform.s3.us-west-2.amazonaws.com/listing/136426-474343-dhwmIbuk3oWYmg45pd9jOOtlKlmmOMn3Feq2T7TM-hs-6963f1f233b2f",
      "photos": [
        "https://hostaway-platform.s3.us-west-2.amazonaws.com/listing/136426-474343-dhwmIbuk3oWYmg45pd9jOOtlKlmmOMn3Feq2T7TM-hs-6963f1f233b2f",
        "https://hostaway-platform.s3.us-west-2.amazonaws.com/listing/136426-474343-H1wAJTTQemZCyN9sIVH34lY86aMiNuDzCNyW1Nbyui4-69613b7216395",
        "https://hostaway-platform.s3.us-west-2.amazonaws.com/listing/136426-474343-qzEre79Ql47S-bCbnNWmBvNsB72QNVasFTf-17zwI7k-6962ea2f1e2b0",
        "https://hostaway-platform.s3.us-west-2.amazonaws.com/listing/136426-474343---DF6qFn7OmbNFEn-ncrhdGnpHIWJudY0Mlc6R758trM-6962ea207bbe8",
        "https://hostaway-platform.s3.us-west-2.amazonaws.com/listing/136426-474343-21gnGYCm4smrzuswKDnFQrA3YJ5g2jNpZ26xib4f-EE-6962ea1cea7f6",
        "https://hostaway-platform.s3.us-west-2.amazonaws.com/listing/136426-474343-ESDFZsQ4GvQmjK5iQVvmmAkrzuHwogPjFsoY8DOxTVg-6962ea2df2871",
        "https://hostaway-platform.s3.us-west-2.amazonaws.com/listing/136426-474343-oK2q8knsAh--xdH5HIYdNKYTTgR--j-xAyGY9pHWckwLk-6962ea31512fa",
        "https://hostaway-platform.s3.us-west-2.amazonaws.com/listing/136426-474343-qXNMG1iihd-Oen4piGThRXm--0DOwwqwuipu0HZG1GHE-6962ea2cdb478",
        "https://hostaway-platform.s3.us-west-2.amazonaws.com/listing/136426-474343-QwmS3chAMJVcvrKKusWOXY9PJK8ottRBN2eqYLewA90-6962ea2b714a8",
        "https://hostaway-platform.s3.us-west-2.amazonaws.com/listing/136426-474343-7vV2L-EuGIsXFKPnLa2tCRaIDWntx4eoAYwenM0FTt4-6962ea2212dd3",
        "https://hostaway-platform.s3.us-west-2.amazonaws.com/listing/136426-474343-ZbUoQwocs15QebH2R7ShKPw5MBRcrYyQv--xXFt2OC--8-6962ea233cfc2",
        "https://hostaway-platform.s3.us-west-2.amazonaws.com/listing/136426-474343-f6DtWr58sqra3EHwcdXm0TryyS2qGXi-En96RIkLHoI-69613b90ae855"
      ],
      "description": "Découvrez notre maison 3 étoiles à Givry, nichée dans un village avec une vue exceptionnelle sur les vignes. Ce lieu charmant et paisible accueille jusqu'à 6 personnes, grâce à ses 2 lits doubles, 1 canapé-lit, et un lit parapluie. Pour un séjour sans souci, nous avons pensé à tout : draps, serviettes, lave-linge, sèche-linge, wifi, et TV sont inclus. Profitez d'un cadre viticole incomparable, idéal pour se ressourcer en famille ou entre amis. Cave vin mis à disposition hors période hivernale. Maison de ville 3 étoiles avec vue sur les vignes Charmante maison de ville classée 3 étoiles, offrant un balcon privatif avec vue sur les vignes pour chaque chambre, ainsi qu'un espace de stationnement dédié. Vous profiterez d'un environnement paisible en pleine nature viticole. Chambres : Toutes les chambres sont équipées de lits queen-size avec une literie haut de gamme, pour un confort optimal. Un lit parapluie est également disponible sur demande (installation et préparation des draps à organiser avant l'arrivée). Équipements complets : Draps, serviettes et vanity kits sont fournis pour un séjour sans souci. Espaces de vie : Maison sur 2 étages, avec une grande table à manger pour 6 personnes, idéale pour partager des moments conviviaux. Divertissement : TV LED The Frame avec accès à Netflix, ainsi qu'un meuble hifi Pachanga des années 1960 en parfait état de fonctionnement (radio et",
      "amenities": [
        "Wifi",
        "Cuisine équipée",
        "Parking gratuit",
        "Sèche-linge",
        "Lave-vaisselle",
        "Télévision",
        "Chauffage",
        "Balcon",
        "Cheminée",
        "Linge & nécessaire",
        "Fer à repasser",
        "Micro-ondes",
        "Four",
        "Réfrigérateur"
      ],
      "lat": 46.7794574,
      "lng": 4.7076755,
      "mapx": 74.66,
      "mapy": 70.7,
      "type": "T3",
      "cleaningFee": 65,
      "deposit": 400,
      "markup": 1.05,
      "minNights": 1,
      "currency": "EUR",
      "instant": 1,
      "reviewCount": 80,
      "reviews": [
        {
          "name": "Voyageur",
          "text": "Très jolie maison de village, bien équipée et décorée avec soin. Check in et communication avec l’hôte très facile. Située à proximité des vignes, sentiers de randonnée accessible à pied. Super week-end merci !"
        },
        {
          "name": "Leonard",
          "text": "Un très beau week-end au calme dans ce logement qui correspond aux attentes. Décoré avec goût et soin."
        },
        {
          "name": "Celine",
          "text": "Jolie maison de village, très bien équipée."
        }
      ]
    },
    {
      "id": 465404,
      "name": "Château de Dracy - L’Élégante",
      "city": "Dracy-le-Fort",
      "guests": 4,
      "bedrooms": 2,
      "bathrooms": 1,
      "price": 120,
      "rating": 9.7,
      "cover": "https://hostaway-platform.s3.us-west-2.amazonaws.com/listing/136426-465404-UtCQdhC3rp8dY--92OhO-bL---hTJSv-f--5f3oLqkcXmk-6a25f8585469c",
      "photos": [
        "https://hostaway-platform.s3.us-west-2.amazonaws.com/listing/136426-465404-UtCQdhC3rp8dY--92OhO-bL---hTJSv-f--5f3oLqkcXmk-6a25f8585469c",
        "https://hostaway-platform.s3.us-west-2.amazonaws.com/listing/136426-465404-SZqVsyToeVFrUuT1NV6BYWQW8BY4Rch6cnVJktsrToQ-6a25ff693f7da",
        "https://hostaway-platform.s3.us-west-2.amazonaws.com/listing/136426-465404-GvFS20Bc5LIKcfiG4a6l2A5kWVXXP5GVvLv8IvSgAtg-6a26069a2b195",
        "https://hostaway-platform.s3.us-west-2.amazonaws.com/listing/136426-465404-eCaeS5xmzUmJ-yYal3EXcOAN8AX7Zx5kp9q9WggnmOA-6a25f86d12336",
        "https://hostaway-platform.s3.us-west-2.amazonaws.com/listing/136426-465404-qONcRIB-5ly1xGivkJa-bbJiKAf6Sga4JZov5AVFo0A-6a25ff64a97a3",
        "https://hostaway-platform.s3.us-west-2.amazonaws.com/listing/136426-465404-h5TpdCPpHpupmrpLeeR9FcuXrl29hjelp3G5s7qBgxU-6a25ff6382614",
        "https://hostaway-platform.s3.us-west-2.amazonaws.com/listing/136426-465404-FM--RoP7fNpCzmuTELo08BSWnbXefbiO47i36QUver84-6a25ff65734b1",
        "https://hostaway-platform.s3.us-west-2.amazonaws.com/listing/136426-465404-eQG6vJXzTXDq2HNkAqEki-KJdEAdiPtt2cNKVAF0nYM-6a26069956474",
        "https://hostaway-platform.s3.us-west-2.amazonaws.com/listing/136426-465404-Cv4fse--kofefVXIey8-2p8hEFIr4--UTNjAu50jOHeqY-6a25f86886521",
        "https://hostaway-platform.s3.us-west-2.amazonaws.com/listing/136426-465404-naQoGa-xCy9O2vBU323z6NJ3zUmRAw--uE12igT0X6TQ-6a25ff68418b3",
        "https://hostaway-platform.s3.us-west-2.amazonaws.com/listing/136426-465404-gNDLFabViCWEdmazXxzNaaEam6eJkc1tMNWndHZZGOE-6a25ff6779439",
        "https://hostaway-platform.s3.us-west-2.amazonaws.com/listing/136426-465404-XdddnipGQZu9X20EeSog-9lc4jOY-mf0br8--6jZYb64-6a2606986e7d4"
      ],
      "description": "Découvrez et savourez le charme unique et Historique du Château de Dracy-le-Fort datant du XIIème siècle avec notre T3 moderne de 70m2. Parfait pour accueillir confortablement une famille, des amis ou encore des aventuriers. L’emplacement est idéal si vous êtes en quête d’inspiration, d'aventure ou de détente. Proche des plus grands domaines viticoles de France, venez vivre un séjour fantastique et inoubliable ! Dès votre entrée, vous serez accueilli dans un sas d'entrée raffiné, équipé d'un GRAND MIROIR aux courbes élégantes et d'un petit meuble pratique pour déposer vos objets du quotidien et parcourir une sélection de livres à votre disposition. → Un WC indépendant est judicieusement placé à gauche pour plus de commodité. → Face à vous, découvrez une salle de bain spacieuse, avec un renfoncement accueillant deux petits patères pour vos serviettes ou peignoirs, un double meuble vasque avec un grand miroir, un sèche-serviette, une BAIGNOIRE et un BAC À DOUCHE, offrant une expérience de bien-être. → Sur la droite, entrez dans une CUISINE ÉQUIPÉE avec un espace repas vintage qui se fond dans le séjour, séparé visuellement par du carrelage côté cuisine et du parquet côté salon. → Le séjour lui-même est agencé avec un sofa et un fauteuil assortis, une table basse en verre et en bois posée sur un tapis en jute, un meuble TV élégant et une TÉLÉVISION MURALE, complété par une CHEMINÉ",
      "amenities": [
        "Wifi",
        "Cuisine équipée",
        "Parking gratuit",
        "Climatisation",
        "Lave-vaisselle",
        "Télévision",
        "Chauffage",
        "Linge & nécessaire",
        "Fer à repasser",
        "Micro-ondes",
        "Four",
        "Réfrigérateur",
        "Séjours longue durée"
      ],
      "lat": 46.79901651,
      "lng": 4.76616338,
      "mapx": 75.96,
      "mapy": 69.89,
      "type": "T3",
      "cleaningFee": 50,
      "deposit": 400,
      "markup": 1.05,
      "minNights": 1,
      "currency": "EUR",
      "instant": 1,
      "reviewCount": 65,
      "reviews": [
        {
          "name": "Francine",
          "text": "Très beau logement, équipements au top, linges de lit de très bonnes qualités. La propreté est irréprochable."
        },
        {
          "name": "Voyageur",
          "text": "Un très bon week-end passé chez Anthony, le château est calme et agréable. Nous reviendrons avec plaisir."
        }
      ]
    }
  ],
  "extras": [
    {
      "id": 497952,
      "name": "La Croix Du Sud",
      "city": "La Londe-les-Maures",
      "guests": 8,
      "bedrooms": 4,
      "bathrooms": 4,
      "price": 2000,
      "rating": null,
      "cover": "https://hostaway-platform.s3.us-west-2.amazonaws.com/listing/136426-497952-bicpmOVHFG4cjq0--se4NZHnsgWhMcTNl8DX2OZl7IO4-69b97468722e4",
      "photos": [
        "https://hostaway-platform.s3.us-west-2.amazonaws.com/listing/136426-497952-bicpmOVHFG4cjq0--se4NZHnsgWhMcTNl8DX2OZl7IO4-69b97468722e4",
        "https://hostaway-platform.s3.us-west-2.amazonaws.com/listing/136426-497952-L2afyRJbLumSbTrUoduBBI--hQNZlDDOo4VpZB4TSds8-69b974486f988",
        "https://hostaway-platform.s3.us-west-2.amazonaws.com/listing/136426-497952-PSSilmdfzPtH3jAFn8Bsp-gXbepyVcLuW3hXchJAm6k-69b9744b7e42f",
        "https://hostaway-platform.s3.us-west-2.amazonaws.com/listing/136426-497952-G-zUnOkhbhuycZvSbFT7DXGiNHHHOfCNRUrvO--ycecE-69b974496d021",
        "https://hostaway-platform.s3.us-west-2.amazonaws.com/listing/136426-497952-UdlniUWLdadRInNNNVjFZeYtuk97FbWxdFXAKvJycjs-69b9745c9f0d7",
        "https://hostaway-platform.s3.us-west-2.amazonaws.com/listing/136426-497952-q74sFSfKTPjej6JMCaWuYBCYMcVtgPFbFzDzeGbqKto-69b974409d451",
        "https://hostaway-platform.s3.us-west-2.amazonaws.com/listing/136426-497952-n2kHtFdfVSL1mNOcmby6ojD-0u--RQDeBQbplEUUm--tA-69b97465d4d07",
        "https://hostaway-platform.s3.us-west-2.amazonaws.com/listing/136426-497952-40o34WEO0otJffmii2t9NDJ84AIxk1tJKKYTCqcaMJo-69b974435b127",
        "https://hostaway-platform.s3.us-west-2.amazonaws.com/listing/136426-497952-AHBuGBTm8u6XeFbL8r2fI81zvXXT0KFbPdp6nsam-HY-69b974453287e",
        "https://hostaway-platform.s3.us-west-2.amazonaws.com/listing/136426-497952-7QyhI5ywhVcvfEkRDwUceiuUtRnzbxhn0qfXVNoHlCs-69b97c36aacec",
        "https://hostaway-platform.s3.us-west-2.amazonaws.com/listing/136426-497952-z--M7OA44RaeM8qo1mdPFtmyAGrXAGx5a8sUjVlLmCYE-69b974443339d",
        "https://hostaway-platform.s3.us-west-2.amazonaws.com/listing/136426-497952-nJad--5qWDU2--SrcXEv7fdouIMrgoDoQquFkVgAEgFaA-69b974463f88f"
      ],
      "description": "Superbe villa de 220 m², lumineuse et élégante, offrant une vue panoramique sur la mer, une piscine à débordement et des prestations haut de gamme. Idéale pour 8 personnes, avec 4 chambres et 4 salles de bain, dans un environnement calme et privilégié. Idéalement située à LA LONDE LES MAURES, au cœur du domaine prisé de Valcros, la CROIX DU SUD, est l’endroit parfait pour des vacances en famille ou entre amis. A proximité du golf de Valcros, cette villa moderne et lumineuse vous offre un cadre paisible, entouré de nature, avec une superbe vue sur les collines, la mer et les iles d’or. La villa peut accueillir jusqu’à 8 voyageurs, grâce à ses 4 chambres confortables, chacune avec sa salle d’eau privative et son ventilateur. Chaque chambre est équipée de lits doubles et de nombreux rangements. La cuisine ouverte entièrement équipée (cafetière Nespresso, grille-pain, bouilloire…) devient rapidement le cœur de la maison. On y prépare un déjeuner léger avant de profiter de la piscine à débordement, ou d’un diner convivial que l’on déguste sur la terrasse, à l’abri des regards, pendant que le soleil disparait derrière la colline. Un extérieur ou le temps ralenti, le jardin méditerranéen entoure la villa comme un écrin de verdure. La piscine devient un lieu de rendez-vous des journées d’été, les transats invitent à la sieste à l’ombre d’un parasol. Après une journée de détente, chacun",
      "amenities": [
        "Wifi",
        "Cuisine équipée",
        "Parking gratuit",
        "Piscine",
        "Sèche-linge",
        "Lave-vaisselle",
        "Télévision",
        "Chauffage",
        "Jardin",
        "Entrée privée",
        "Linge & nécessaire",
        "Fer à repasser",
        "Micro-ondes",
        "Four"
      ],
      "lat": 43.1760769,
      "lng": 6.2845245,
      "mapx": null,
      "mapy": null,
      "type": "T5",
      "cleaningFee": 300,
      "deposit": 400,
      "markup": 0.9,
      "minNights": 1,
      "currency": "EUR",
      "instant": 1
    },
    {
      "id": 496304,
      "name": "Le Megevand",
      "city": "Demi-Quartier",
      "guests": 8,
      "bedrooms": 4,
      "bathrooms": 3,
      "price": 436,
      "rating": 0,
      "cover": "https://hostaway-platform.s3.us-west-2.amazonaws.com/listing/136426-496304-3j--2QozKBeK6dxiqYyYeQQhpaZfoln7zrUT-UwQcq20-69b296a9a68f5",
      "photos": [
        "https://hostaway-platform.s3.us-west-2.amazonaws.com/listing/136426-496304-3j--2QozKBeK6dxiqYyYeQQhpaZfoln7zrUT-UwQcq20-69b296a9a68f5",
        "https://hostaway-platform.s3.us-west-2.amazonaws.com/listing/136426-496304-LHI9M4gSMvIaLttJxqw-xt4v1Fob5Fxk6I0B4cjgvJ4-69b296ae31b96",
        "https://hostaway-platform.s3.us-west-2.amazonaws.com/listing/136426-496304-lmAt---yTpVZ3Mbub--yHTsK8gofShf--8RP7bX5IJTLEg-69b296a573f57",
        "https://hostaway-platform.s3.us-west-2.amazonaws.com/listing/136426-496304-bMrRsTNUoffFti1R6aVsnaJeFbDCfFuAEr2z503TCFo-69b296a793dea",
        "https://hostaway-platform.s3.us-west-2.amazonaws.com/listing/136426-496304-v1HGcryxNAlJPjFpAwVv-hE--PFuI1hqNnIuv84W-1Qg-69b29699100c9",
        "https://hostaway-platform.s3.us-west-2.amazonaws.com/listing/136426-496304-r0SUWjWKKsfMX9gdWoqiLdFOLBTdUCNyDrRARfazTp4-69b2961d150dd",
        "https://hostaway-platform.s3.us-west-2.amazonaws.com/listing/136426-496304-ZYWgqtfyCWIhNLDOTqJpTTnp6O2VGx7X--6g1lj2Z1R0-69b2961ad54dd",
        "https://hostaway-platform.s3.us-west-2.amazonaws.com/listing/136426-496304-lqhRHcA7H7mdbuSmDbuROksWEVcHzQnWhzAYP5OhCKs-69b2961fd9454",
        "https://hostaway-platform.s3.us-west-2.amazonaws.com/listing/136426-496304-6p4Qp8PrXIyUlNeRfNF--BaB1H6fy0aY31MzezUZH4xY-69b29623645ff",
        "https://hostaway-platform.s3.us-west-2.amazonaws.com/listing/136426-496304-9YLoPnEJkIs7iMGzLuBka7HQsneYdzwmoBTgx-c6p8I-69b296a3476c2",
        "https://hostaway-platform.s3.us-west-2.amazonaws.com/listing/136426-496304-gOAZ151nOh3cyg7q-3QKxN--pk2bTy--yF8IOlXy9ifSs-69b2969cb85cb",
        "https://hostaway-platform.s3.us-west-2.amazonaws.com/listing/136426-496304-gH1bukK-SPUOFjKheWfM5TgwSS--3cEiQtHalWUQvuHw-69b29615b3fcc"
      ],
      "description": "Passez un agréable séjour dans cet hébergement confortable.",
      "amenities": [
        "Wifi",
        "Cuisine équipée",
        "Parking gratuit",
        "Télévision",
        "Chauffage",
        "Cheminée",
        "Linge & nécessaire",
        "Micro-ondes",
        "Réfrigérateur",
        "Séjours longue durée"
      ],
      "lat": 45.8668478,
      "lng": 6.6241973,
      "mapx": null,
      "mapy": null,
      "type": "T5",
      "cleaningFee": 300,
      "deposit": 400,
      "markup": 1.05,
      "minNights": 7,
      "currency": "EUR",
      "instant": 1
    }
  ],
  "reviews": [
    {
      "name": "Voyageur",
      "place": "Chalon-sur-Saône",
      "text": "un excellent logement pour quiconque souhaite passer un week end à chalon sur saone. Situer au coeur du centre-ville, cet appartement rend facile d'accès tous les restaurants et boutiques tout en restant confortable. Je recommande"
    },
    {
      "name": "Veronique",
      "place": "Fragnes-La Loyère",
      "text": "Nous avons passé un excellent séjour. Christian est un hôte très sympathique. L appartement correspond bien au descriptif. Literie très confortable. L endroit est très paisible et propice aux ballades . Vue magnifique sur le canal"
    },
    {
      "name": "Carlos",
      "place": "La Charmée",
      "text": "Maison conforme à la description, très propre, bien rangé et parfaitement équipé (très complet) dans un écrin de verdure et extrêmement paisible. Véronique s'est montrée extrêmement accueillante et à l'écoute. Nous recommandons !"
    },
    {
      "name": "Martha",
      "place": "Mâcon",
      "text": "Logement très agréable et spacieux. Bon emplacement pour accéder au centre ville et bords de Saône. Arrivée autonome sans encombre. Nous nous sommes garés sur le parking gratuit de la gare, il n'y avait pas de place dans la rue."
    },
    {
      "name": "Hamouda",
      "place": "Chalon-sur-Saône",
      "text": "Logement facile d’accès, très bien situé. Le propriétaire est à l’écoute, disponible et présent en cas de besoin. Le logement est propre, pratique et fonctionnel. Très bon rapport qualité/prix. Je recommande sans hésitation."
    },
    {
      "name": "Aurelien",
      "place": "Dracy-le-Fort",
      "text": "Logement correspondant parfaitement à la description. Décoré avec goût, cave magnifique, pièce de vie très agréable à vivre. Juste dommage qu il n y est pas 8 verres à vin afin de profiter pleinement de cette fabuleuse cave."
    }
  ],
  "updated": "2026-07-05"
}